pyTemplate/run.py
pyTemplateBath/__init__.py
pyTemplateBath/hello.py
pyTemplateBath/main.py
pyTemplateBath/run.py
pyTemplateBath-0.1.1.data/scripts/pyTemplateBath
pyTemplateSR/run.py
pyTemplateBath-0.1.1.dist-info/LICENSE
pyTemplateBath-0.1.1.dist-info/METADATA
pyTemplateBath-0.1.1.dist-info/WHEEL
pyTemplateBath-0.1.1.dist-info/top_level.txt
pyTemplateBath-0.1.1.dist-info/RECORD
